nnde/__init__.py
nnde/differentialequation/__init__.py
nnde/differentialequation/differentialequation.py
nnde/differentialequation/examples/__init__.py
nnde/differentialequation/examples/diff1d_half.py
nnde/differentialequation/examples/diff1d_halfsine.py
nnde/differentialequation/examples/diff1d_halfsine_increase.py
nnde/differentialequation/examples/diff1d_one.py
nnde/differentialequation/examples/diff1d_zero.py
nnde/differentialequation/examples/diff2d_halfsine.py
nnde/differentialequation/examples/diff2d_halfsine_increase.py
nnde/differentialequation/examples/diff3d_halfsine.py
nnde/differentialequation/examples/diff3d_halfsine_increase.py
nnde/differentialequation/examples/example_pde1ivp_01.py
nnde/differentialequation/examples/lagaris_01.py
nnde/differentialequation/examples/lagaris_02.py
nnde/differentialequation/examples/tests/__init__.py
nnde/differentialequation/examples/tests/test_diff1d_half.py
nnde/differentialequation/examples/tests/test_diff1d_halfsine.py
nnde/differentialequation/examples/tests/test_diff1d_halfsine_increase.py
nnde/differentialequation/examples/tests/test_diff1d_one.py
nnde/differentialequation/examples/tests/test_diff1d_zero.py
nnde/differentialequation/examples/tests/test_diff2d_halfsine.py
nnde/differentialequation/examples/tests/test_diff2d_halfsine_increase.py
nnde/differentialequation/examples/tests/test_diff3d_halfsine.py
nnde/differentialequation/examples/tests/test_diff3d_halfsine_increase.py
nnde/differentialequation/examples/tests/test_example_pde1ivp_01.py
nnde/differentialequation/examples/tests/test_lagaris_01.py
nnde/differentialequation/examples/tests/test_lagaris_02.py
nnde/differentialequation/ode/__init__.py
nnde/differentialequation/ode/ode.py
nnde/differentialequation/ode/ode1.py
nnde/differentialequation/ode/ode1ivp.py
nnde/differentialequation/ode/tests/__init__.py
nnde/differentialequation/ode/tests/test_ODE.py
nnde/differentialequation/ode/tests/test_ODE1.py
nnde-0.0.7.dist-info/LICENSE
nnde-0.0.7.dist-info/METADATA
nnde-0.0.7.dist-info/WHEEL
nnde-0.0.7.dist-info/top_level.txt
nnde-0.0.7.dist-info/RECORD
