Metadata-Version: 2.1
Name: nnde
Version: 0.0.7
Summary: A package implementing a collection of neural networks to solve ordinary and partial differential equations
Home-page: https://github.com/elwinter/nnde
Author: Eric Winter
Author-email: eric.winter62@gmail.com
License: UNKNOWN
Platform: UNKNOWN
Classifier: Programming Language :: Python :: 3
Classifier: License :: OSI Approved :: GNU Lesser General Public License v3 (LGPLv3)
Classifier: Operating System :: OS Independent
Requires-Python: >=3.6
